template_creator/__init__.py
template_creator/command_line.py
template_creator/coordinator.py
template_creator/middleware/__init__.py
template_creator/middleware/transformer.py
template_creator/reader/FileInfo.py
template_creator/reader/__init__.py
template_creator/reader/directory_scanner.py
template_creator/reader/config/__init__.py
template_creator/reader/config/iam_config.py
template_creator/reader/strategies/GoStrategy.py
template_creator/reader/strategies/PythonStrategy.py
template_creator/reader/strategies/__init__.py
template_creator/reader/strategies/language_strategy_builder.py
template_creator/reader/strategies/language_strategy_common.py
template_creator/util/__init__.py
template_creator/util/constants.py
template_creator/util/input_checks.py
template_creator/util/template_checks.py
template_creator/util/template_errors.py
template_creator/writer/__init__.py
template_creator/writer/header_writer.py
template_creator/writer/lambda_writer.py
template_creator/writer/yaml_writer.py
sam_template_creator-0.1.3.dist-info/LICENSE
sam_template_creator-0.1.3.dist-info/METADATA
sam_template_creator-0.1.3.dist-info/WHEEL
sam_template_creator-0.1.3.dist-info/entry_points.txt
sam_template_creator-0.1.3.dist-info/top_level.txt
sam_template_creator-0.1.3.dist-info/RECORD
