Metadata-Version: 2.1
Name: sam-template-creator
Version: 0.1.3
Summary: Creates a SAM template for a given project
Home-page: https://github.com/VanOvermeire/sam-template-creator
Author: Sam Van Overmeire
Author-email: sam.van.overmeire@hotmail.com
License: MIT
Platform: UNKNOWN
Requires-Dist: ruamel.yaml (>=0.15.89)
